LICENSE
MANIFEST.in
README.md
requirements.txt
setup.py
belaweb/__init__.py
belaweb/__version__.py
belaweb/admin.py
belaweb/apps.py
belaweb/forms.py
belaweb/models.py
belaweb/tests.py
belaweb/urls.py
belaweb/views.py
belaweb.egg-info/PKG-INFO
belaweb.egg-info/SOURCES.txt
belaweb.egg-info/dependency_links.txt
belaweb.egg-info/requires.txt
belaweb.egg-info/top_level.txt
belaweb/belaviz/__init__.py
belaweb/belaviz/bela1viz.py
belaweb/belaviz/bela2viz.py
belaweb/belaviz/common.py
belaweb/belaviz/langmixviz.py
belaweb/migrations/0001_initial.py
belaweb/migrations/__init__.py
belaweb/public/__init__.py
belaweb/public/apps.py
belaweb/public/urls.py
belaweb/public/views.py
belaweb/static/vendor/bela-dashboard/bela-dashboard.js
belaweb/static/vendor/chart.js/Chart.bundle.min.js
belaweb/static/vendor/chart.js/Chart.min.js
belaweb/templates/belaweb/bela_langbars.html
belaweb/templates/belaweb/bela_lexicon.html
belaweb/templates/belaweb/bela_public.html
belaweb/templates/belaweb/bela_visual.html
belaweb/templates/belaweb/format_error.html
belaweb/templates/belaweb/home.html